jidoka/__init__.py
jidoka-0.1.0.dist-info/LICENSE.md
jidoka-0.1.0.dist-info/WHEEL
jidoka-0.1.0.dist-info/METADATA
jidoka-0.1.0.dist-info/RECORD
